remi_z
