Metadata-Version: 2.1
Name: REMI-z
Version: 0.5.9
Summary: Manipulate your MIDI file in bar level, and converting between MIDI and REMI-z format.
Home-page: https://github.com/Sonata165/REMI-z
Author: Longshen Ou
Author-email: oulongshen@gmail.com
License: MIT
Classifier: Programming Language :: Python :: 3
Classifier: License :: OSI Approved :: MIT License
Classifier: Operating System :: OS Independent
Classifier: Intended Audience :: Developers
Classifier: Topic :: Multimedia :: Sound/Audio :: MIDI
Requires-Python: >=3.7
License-File: LICENSE
Requires-Dist: miditoolkit==1.0.1
Requires-Dist: music21==9.3.0
Requires-Dist: pretty_midi==0.2.10
Requires-Dist: pyyaml==6.0.2
